{
    "alerta": "ANOMALIA_GABINETE",
    "metadados": {
        "external_id": "camara_141408",
        "total_anomalias": 15,
        "detalhes": [
            {
                "supplier": "MARIA RAQUEL DA SILVA BORGMANN",
                "totalValue": 55000.0,
                "paymentCount": 10,
                "flags": [
                    {
                        "type": "CONCENTRACAO",
                        "severity": "MEDIUM",
                        "detail": "Recebe apenas deste deputado. 10 pagamentos totalizando R$55,000.00"
                    }
                ]
            },
            {
                "supplier": "ALYSSON  PENHA SILVA",
                "totalValue": 52000.0,
                "paymentCount": 13,
                "flags": [
                    {
                        "type": "CONCENTRACAO",
                        "severity": "MEDIUM",
                        "detail": "Recebe apenas deste deputado. 13 pagamentos totalizando R$52,000.00"
                    }
                ]
            },
            {
                "supplier": "Sistema Inga de Comunicão Ltda",
                "totalValue": 52000.0,
                "paymentCount": 6,
                "flags": [
                    {
                        "type": "CONCENTRACAO",
                        "severity": "MEDIUM",
                        "detail": "Recebe apenas deste deputado. 6 pagamentos totalizando R$52,000.00"
                    }
                ]
            },
            {
                "supplier": "TAM",
                "totalValue": 20040.12,
                "paymentCount": 13,
                "flags": [
                    {
                        "type": "ML_ANOMALIA",
                        "severity": "LOW",
                        "detail": "Detectado por Isolation Forest (score: -0.3262)"
                    }
                ]
            },
            {
                "supplier": "Azul Linhas Aéreas",
                "totalValue": 12765.75,
                "paymentCount": 12,
                "flags": [
                    {
                        "type": "ML_ANOMALIA",
                        "severity": "LOW",
                        "detail": "Detectado por Isolation Forest (score: -0.3227)"
                    }
                ]
            },
            {
                "supplier": "SETE CORES INDÚSTRIA E COMÉRCIO LTDA",
                "totalValue": 93000.0,
                "paymentCount": 1,
                "flags": [
                    {
                        "type": "ML_ANOMALIA",
                        "severity": "LOW",
                        "detail": "Detectado por Isolation Forest (score: -0.0822)"
                    }
                ]
            },
            {
                "supplier": "SHEKINAH COMUNICACAO E MARKETING LTDA",
                "totalValue": 93000.0,
                "paymentCount": 1,
                "flags": [
                    {
                        "type": "ML_ANOMALIA",
                        "severity": "LOW",
                        "detail": "Detectado por Isolation Forest (score: -0.0822)"
                    }
                ]
            },
            {
                "supplier": "AZUL",
                "totalValue": 8798.39,
                "paymentCount": 11,
                "flags": [
                    {
                        "type": "ML_ANOMALIA",
                        "severity": "LOW",
                        "detail": "Detectado por Isolation Forest (score: -0.3262)"
                    }
                ]
            },
            {
                "supplier": "GOL",
                "totalValue": 5345.96,
                "paymentCount": 4,
                "flags": [
                    {
                        "type": "ML_ANOMALIA",
                        "severity": "LOW",
                        "detail": "Detectado por Isolation Forest (score: -0.3262)"
                    }
                ]
            },
            {
                "supplier": "EMIDIO SOUTO PEREIRA",
                "totalValue": 2321.8,
                "paymentCount": 8,
                "flags": [
                    {
                        "type": "ML_ANOMALIA",
                        "severity": "LOW",
                        "detail": "Detectado por Isolation Forest (score: -0.1180)"
                    }
                ]
            },
            {
                "supplier": "LATAM Airlines Brasil",
                "totalValue": 2223.36,
                "paymentCount": 1,
                "flags": [
                    {
                        "type": "ML_ANOMALIA",
                        "severity": "LOW",
                        "detail": "Detectado por Isolation Forest (score: -0.3262)"
                    }
                ]
            },
            {
                "supplier": "Gol Linhas Aéreas",
                "totalValue": 2144.21,
                "paymentCount": 1,
                "flags": [
                    {
                        "type": "ML_ANOMALIA",
                        "severity": "LOW",
                        "detail": "Detectado por Isolation Forest (score: -0.3227)"
                    }
                ]
            },
            {
                "supplier": "GOMO COMUNICAÇÂO LTDA",
                "totalValue": 2000.0,
                "paymentCount": 1,
                "flags": [
                    {
                        "type": "ML_ANOMALIA",
                        "severity": "LOW",
                        "detail": "Detectado por Isolation Forest (score: -0.1651)"
                    }
                ]
            },
            {
                "supplier": "EMYSOUTO PAPELARIA INFORMATICA E LIMPEZA LTDA",
                "totalValue": 919.8,
                "paymentCount": 5,
                "flags": [
                    {
                        "type": "ML_ANOMALIA",
                        "severity": "LOW",
                        "detail": "Detectado por Isolation Forest (score: -0.0772)"
                    }
                ]
            },
            {
                "supplier": "ELDORADO COMUNICACAO E JORNALISMO LTDA",
                "totalValue": 140000.0,
                "paymentCount": 12,
                "flags": [
                    {
                        "type": "ML_ANOMALIA",
                        "severity": "LOW",
                        "detail": "Detectado por Isolation Forest (score: -0.3013)"
                    }
                ]
            }
        ]
    }
}